LICENSE.txt
README.md
setup.cfg
setup.py
nomhsms/__init__.py
nomhsms/__main__.py
nomhsms/__version__.py
nomhsms/brutto.py
nomhsms/diff.py
nomhsms/draw.py
nomhsms/gui.py
nomhsms/gui_design.py
nomhsms/gui_dialog.py
nomhsms/metadata.py
nomhsms/recal.py
nomhsms/spectra.py
nomhsms/spectrum.py
nomhsms.egg-info/PKG-INFO
nomhsms.egg-info/SOURCES.txt
nomhsms.egg-info/dependency_links.txt
nomhsms.egg-info/requires.txt
nomhsms.egg-info/top_level.txt